statement_dl/__init__.py
statement_dl/__main__.py
statement_dl/flatex.py
statement_dl/utils.py
statement_dl-2023.7.1.dist-info/LICENSE
statement_dl-2023.7.1.dist-info/METADATA
statement_dl-2023.7.1.dist-info/WHEEL
statement_dl-2023.7.1.dist-info/entry_points.txt
statement_dl-2023.7.1.dist-info/top_level.txt
statement_dl-2023.7.1.dist-info/RECORD
