Metadata-Version: 2.1
Name: statement-dl
Version: 2023.7.1
Summary: Automatic download of banking/broker documents from flatex
Home-page: https://github.com/pspeter/statement-dl
Author: Peter Schmidbauer
Author-email: peter.schmidb@gmail.com
License: MIT
Classifier: Programming Language :: Python :: 3.8
Classifier: Programming Language :: Python :: 3.9
Classifier: Programming Language :: Python :: 3.10
Classifier: Programming Language :: Python :: 3.11
Classifier: License :: OSI Approved :: MIT License
Classifier: Operating System :: OS Independent
Requires-Python: >=3.8
License-File: LICENSE
Requires-Dist: selenium (==4.*)
